[
  {
    "line": 4,
    "elements": [
      {
        "start_timestamp": "2022-02-04T03:29:26.594Z",
        "before": [
          {
            "result": {
              "duration": 1113000,
              "status": "passed"
            },
            "match": {
              "location": "ScenarioDefinitions.HooksLoginSteps.browserSetUP()"
            }
          },
          {
            "result": {
              "duration": 5724152000,
              "status": "passed"
            },
            "match": {
              "location": "ScenarioDefinitions.BackgroundSteps.browserSetup()"
            }
          }
        ],
        "line": 7,
        "name": "Title of your scenario",
        "description": "",
        "id": "login-featutre-with-hooks-concept;title-of-your-scenario",
        "after": [
          {
            "result": {
              "duration": 199700000,
              "status": "passed"
            },
            "match": {
              "location": "ScenarioDefinitions.BackgroundSteps.closeBrowserInstance()"
            }
          },
          {
            "result": {
              "duration": 1115000,
              "status": "passed"
            },
            "match": {
              "location": "ScenarioDefinitions.HooksLoginSteps.closeBrowserInstance()"
            }
          }
        ],
        "type": "scenario",
        "keyword": "Scenario",
        "steps": [
          {
            "result": {
              "duration": 430000,
              "status": "passed"
            },
            "before": [
              {
                "result": {
                  "duration": 371000,
                  "status": "passed"
                },
                "match": {
                  "location": "ScenarioDefinitions.HooksLoginSteps.beforeSteps()"
                }
              },
              {
                "result": {
                  "duration": 167000,
                  "status": "passed"
                },
                "match": {
                  "location": "ScenarioDefinitions.HooksLoginSteps.beforeSteps1()"
                }
              }
            ],
            "line": 8,
            "name": "Hook- Browser is open",
            "match": {
              "location": "ScenarioDefinitions.HooksLoginSteps.hook_browser_is_open()"
            },
            "after": [
              {
                "result": {
                  "duration": 135000,
                  "status": "passed"
                },
                "match": {
                  "location": "ScenarioDefinitions.HooksLoginSteps.afterSteps1()"
                }
              },
              {
                "result": {
                  "duration": 108000,
                  "status": "passed"
                },
                "match": {
                  "location": "ScenarioDefinitions.HooksLoginSteps.afterSteps()"
                }
              }
            ],
            "keyword": "Given "
          },
          {
            "result": {
              "duration": 220000,
              "status": "passed"
            },
            "before": [
              {
                "result": {
                  "duration": 754000,
                  "status": "passed"
                },
                "match": {
                  "location": "ScenarioDefinitions.HooksLoginSteps.beforeSteps()"
                }
              },
              {
                "result": {
                  "duration": 208000,
                  "status": "passed"
                },
                "match": {
                  "location": "ScenarioDefinitions.HooksLoginSteps.beforeSteps1()"
                }
              }
            ],
            "line": 9,
            "name": "Hook- User is in login page",
            "match": {
              "location": "ScenarioDefinitions.HooksLoginSteps.hook_user_is_in_login_page()"
            },
            "after": [
              {
                "result": {
                  "duration": 168000,
                  "status": "passed"
                },
                "match": {
                  "location": "ScenarioDefinitions.HooksLoginSteps.afterSteps1()"
                }
              },
              {
                "result": {
                  "duration": 199000,
                  "status": "passed"
                },
                "match": {
                  "location": "ScenarioDefinitions.HooksLoginSteps.afterSteps()"
                }
              }
            ],
            "keyword": "And "
          },
          {
            "result": {
              "duration": 295000,
              "status": "passed"
            },
            "before": [
              {
                "result": {
                  "duration": 175000,
                  "status": "passed"
                },
                "match": {
                  "location": "ScenarioDefinitions.HooksLoginSteps.beforeSteps()"
                }
              },
              {
                "result": {
                  "duration": 265000,
                  "status": "passed"
                },
                "match": {
                  "location": "ScenarioDefinitions.HooksLoginSteps.beforeSteps1()"
                }
              }
            ],
            "line": 10,
            "name": "Hook- Enter username and password",
            "match": {
              "location": "ScenarioDefinitions.HooksLoginSteps.hook_enter_username_and_password()"
            },
            "after": [
              {
                "result": {
                  "duration": 967000,
                  "status": "passed"
                },
                "match": {
                  "location": "ScenarioDefinitions.HooksLoginSteps.afterSteps1()"
                }
              },
              {
                "result": {
                  "duration": 250000,
                  "status": "passed"
                },
                "match": {
                  "location": "ScenarioDefinitions.HooksLoginSteps.afterSteps()"
                }
              }
            ],
            "keyword": "When "
          },
          {
            "result": {
              "duration": 285000,
              "status": "passed"
            },
            "before": [
              {
                "result": {
                  "duration": 171000,
                  "status": "passed"
                },
                "match": {
                  "location": "ScenarioDefinitions.HooksLoginSteps.beforeSteps()"
                }
              },
              {
                "result": {
                  "duration": 162000,
                  "status": "passed"
                },
                "match": {
                  "location": "ScenarioDefinitions.HooksLoginSteps.beforeSteps1()"
                }
              }
            ],
            "line": 11,
            "name": "Hook- User click on login button",
            "match": {
              "location": "ScenarioDefinitions.HooksLoginSteps.hook_user_click_on_login_button()"
            },
            "after": [
              {
                "result": {
                  "duration": 162000,
                  "status": "passed"
                },
                "match": {
                  "location": "ScenarioDefinitions.HooksLoginSteps.afterSteps1()"
                }
              },
              {
                "result": {
                  "duration": 146000,
                  "status": "passed"
                },
                "match": {
                  "location": "ScenarioDefinitions.HooksLoginSteps.afterSteps()"
                }
              }
            ],
            "keyword": "And "
          },
          {
            "result": {
              "duration": 160000,
              "status": "passed"
            },
            "before": [
              {
                "result": {
                  "duration": 151000,
                  "status": "passed"
                },
                "match": {
                  "location": "ScenarioDefinitions.HooksLoginSteps.beforeSteps()"
                }
              },
              {
                "result": {
                  "duration": 137000,
                  "status": "passed"
                },
                "match": {
                  "location": "ScenarioDefinitions.HooksLoginSteps.beforeSteps1()"
                }
              }
            ],
            "line": 12,
            "name": "Hook- Verify user logged in successfully",
            "match": {
              "location": "ScenarioDefinitions.HooksLoginSteps.hook_verify_user_logged_in_successfully()"
            },
            "after": [
              {
                "result": {
                  "duration": 540000,
                  "status": "passed"
                },
                "match": {
                  "location": "ScenarioDefinitions.HooksLoginSteps.afterSteps1()"
                }
              },
              {
                "result": {
                  "duration": 139000,
                  "status": "passed"
                },
                "match": {
                  "location": "ScenarioDefinitions.HooksLoginSteps.afterSteps()"
                }
              }
            ],
            "keyword": "Then "
          }
        ],
        "tags": [
          {
            "name": "@HookScenario"
          }
        ]
      }
    ],
    "name": "Login featutre with hooks concept",
    "description": "",
    "id": "login-featutre-with-hooks-concept",
    "keyword": "Feature",
    "uri": "file:src/test/resources/Features/loginWithHooks.feature",
    "tags": []
  }
]